git_variables/__init__.py
git_variables/cli.py
git_variables/const.py
git_variables/gitlab_api.py
git_variables/pull.py
git_variables/push.py
git_variables/utils.py
git_variables-0.1.6.dist-info/LICENSE.txt
git_variables-0.1.6.dist-info/METADATA
git_variables-0.1.6.dist-info/WHEEL
git_variables-0.1.6.dist-info/entry_points.txt
git_variables-0.1.6.dist-info/RECORD
