Metadata-Version: 2.1
Name: git-variables
Version: 0.1.6
Summary: Python packages that allows to manage GitLab env variables seamlessly between remote and local respository
License: MIT
Author: Gorka
Author-email: riberagorka@gmail.com
Requires-Python: >=3.10,<4.0
Classifier: License :: OSI Approved :: MIT License
Classifier: Programming Language :: Python :: 3
Classifier: Programming Language :: Python :: 3.10
Classifier: Programming Language :: Python :: 3.11
Classifier: Programming Language :: Python :: 3.12
